ZetcodeServletJiaochengChuyi/README.md
ZetcodeServletJiaochengChuyi/__init__.py
ZetcodeServletJiaochengChuyi/__main__.py
ZetcodeServletJiaochengChuyi/file.epub
ZetcodeServletJiaochengChuyi/index.html
ZetcodeServletJiaochengChuyi/css/__init__.py
ZetcodeServletJiaochengChuyi/css/annotations.css
ZetcodeServletJiaochengChuyi/css/main.css
ZetcodeServletJiaochengChuyi/css/normalize.css
ZetcodeServletJiaochengChuyi/css/popup.css
ZetcodeServletJiaochengChuyi/font/__init__.py
ZetcodeServletJiaochengChuyi/font/fontello.eot
ZetcodeServletJiaochengChuyi/font/fontello.svg
ZetcodeServletJiaochengChuyi/font/fontello.ttf
ZetcodeServletJiaochengChuyi/font/fontello.woff
ZetcodeServletJiaochengChuyi/img/__init__.py
ZetcodeServletJiaochengChuyi/img/annotator-glyph-sprite.png
ZetcodeServletJiaochengChuyi/img/annotator-icon-sprite.png
ZetcodeServletJiaochengChuyi/img/apple-touch-icon.png
ZetcodeServletJiaochengChuyi/img/cancelfullscreen.png
ZetcodeServletJiaochengChuyi/img/close.png
ZetcodeServletJiaochengChuyi/img/fullscreen.png
ZetcodeServletJiaochengChuyi/img/loader.gif
ZetcodeServletJiaochengChuyi/img/menu-icon.png
ZetcodeServletJiaochengChuyi/img/save.png
ZetcodeServletJiaochengChuyi/img/saved.png
ZetcodeServletJiaochengChuyi/img/settings-s.png
ZetcodeServletJiaochengChuyi/img/settings.png
ZetcodeServletJiaochengChuyi/img/star.png
ZetcodeServletJiaochengChuyi/js/__init__.py
ZetcodeServletJiaochengChuyi/js/epub.js
ZetcodeServletJiaochengChuyi/js/epub.min.js
ZetcodeServletJiaochengChuyi/js/epub.min.map
ZetcodeServletJiaochengChuyi/js/hooks.min.js
ZetcodeServletJiaochengChuyi/js/hooks.min.map
ZetcodeServletJiaochengChuyi/js/reader.js
ZetcodeServletJiaochengChuyi/js/reader.js.map
ZetcodeServletJiaochengChuyi/js/reader.min.js
ZetcodeServletJiaochengChuyi/js/reader.min.map
ZetcodeServletJiaochengChuyi/js/hooks/__init__.py
ZetcodeServletJiaochengChuyi/js/hooks/extensions/__init__.py
ZetcodeServletJiaochengChuyi/js/hooks/extensions/highlight.js
zetcode_servlet_jiaocheng_chuyi-2024.3.5.0.dist-info/METADATA
zetcode_servlet_jiaocheng_chuyi-2024.3.5.0.dist-info/WHEEL
zetcode_servlet_jiaocheng_chuyi-2024.3.5.0.dist-info/entry_points.txt
zetcode_servlet_jiaocheng_chuyi-2024.3.5.0.dist-info/top_level.txt
zetcode_servlet_jiaocheng_chuyi-2024.3.5.0.dist-info/RECORD
